genrex/__init__.py
genrex/classes.py
genrex/clustering.py
genrex/enums.py
genrex/genrex.py
genrex/logging.py
genrex/misc.py
genrex/py.typed
genrex/regex.py
genrex/types.py
genrex_py-1.1.1.dist-info/LICENSE.md
genrex_py-1.1.1.dist-info/METADATA
genrex_py-1.1.1.dist-info/WHEEL
genrex_py-1.1.1.dist-info/RECORD
