Metadata-Version: 2.1
Name: genrex-py
Version: 1.1.1
Summary: GenRex is a tool that generates regular expressions from strings such as artifacts dynamically generated by samples.
License: MIT
Author: Dominika Regéciová
Author-email: Dominika.Regeciova@gendigital.com
Maintainer: Dominika Regéciová
Maintainer-email: Dominika.Regeciova@gendigital.com
Requires-Python: >=3.10,<4.0
Classifier: License :: OSI Approved :: MIT License
Classifier: Programming Language :: Python :: 3
Classifier: Programming Language :: Python :: 3.10
Classifier: Programming Language :: Python :: 3.11
Classifier: Programming Language :: Python :: 3.12
